revwhox.py
revwhox-1.1.1.dist-info/METADATA
revwhox-1.1.1.dist-info/WHEEL
revwhox-1.1.1.dist-info/entry_points.txt
revwhox-1.1.1.dist-info/top_level.txt
revwhox-1.1.1.dist-info/RECORD
