Metadata-Version: 2.1
Name: revwhox
Version: 1.1.1
Summary: Find domain names owned by an individual or company using this tool.
Home-page: https://github.com/null3yte/revwhox
Author: null3yte
Author-email: nullmad.eb00@gmail.com
Requires-Dist: setuptools (~=65.5.0)
Requires-Dist: aiohttp (~=3.8.4)
Requires-Dist: bs4 (~=0.0.1)
Requires-Dist: beautifulsoup4 (~=4.12.2)
Requires-Dist: selenium (~=4.10.0)
